fckln-1.0.1.dist-info/licenses/LICENSE
kln/__init__.py
kln/kln.py
fckln-1.0.1.dist-info/METADATA
fckln-1.0.1.dist-info/WHEEL
fckln-1.0.1.dist-info/top_level.txt
fckln-1.0.1.dist-info/RECORD
