Metadata-Version: 2.4
Name: FCKLN
Version: 1.0.1
Summary: Flexible Conditional Modeling for Structured Dependencies
Author-email: Michal Krupa <michalkrupa@gmail.com>
License-Expression: MIT
Project-URL: Homepage, https://github.com/michalkrupa/enterrepohere/
Project-URL: Issues, https://github.com/michalkrupa/enterrepohere/issues
Classifier: Programming Language :: Python :: 3
Classifier: Operating System :: OS Independent
Requires-Python: >=3.8
License-File: LICENSE
Requires-Dist: scipy
Requires-Dist: numpy
Requires-Dist: matplotlib
Requires-Dist: torch
Dynamic: license-file
